{
  "all_results_summary": {
    "5": {
      "combined": {
        "mmr": {
          "count": 300,
          "accuracy": 0.85,
          "tokens": {},
          "response_time": {
            "mean": 1.9404364474614462,
            "std": 2.900772546432111
          },
          "selection_time": {
            "mean": 0.0077679101626078285,
            "std": 0.0063224184620856525
          },
          "total_latency": {
            "mean": 1.948204357624054,
            "std": 2.900718357707198
          }
        }
      }
    }
  },
  "args": {
    "dataset": "combined",
    "data_dir": "./data",
    "num_test_samples": 300,
    "num_repeats": 10,
    "method": "mmr",
    "num_examples": [
      5
    ],
    "lambda_param": 0.7,
    "n_clusters": 5,
    "min_cluster_size": 5,
    "min_samples": null,
    "embedding_model": "all-mpnet-base-v2",
    "force_recompute": false,
    "gpt_model": null,
    "gpt_temperature": null,
    "gpt_max_tokens": null,
    "experiment_name": "combined_mmr_20250523_173555",
    "results_dir": "./results"
  },
  "repeat_index": 5
}